claudette/__init__.py
claudette/cli.py
claudette/config.py
claudette/templates/CLAUDE.local.md
claudette/templates/claude_rc_central
claudette/templates/claude_rc_template
claudette/templates/gitignore_additions
superset_claudette-0.1.6.dist-info/METADATA
superset_claudette-0.1.6.dist-info/WHEEL
superset_claudette-0.1.6.dist-info/entry_points.txt
superset_claudette-0.1.6.dist-info/RECORD
